LICENSE
MANIFEST.in
setup.py
jones/__init__.py
jones/client.py
jones.egg-info/PKG-INFO
jones.egg-info/SOURCES.txt
jones.egg-info/dependency_links.txt
jones.egg-info/not-zip-safe
jones.egg-info/requires.txt
jones.egg-info/top_level.txt