Metadata-Version: 1.0
Name: jones
Version: 0.3.1
Summary: Configuration frontend for Zookeeper.
Home-page: https://github.com/disqus/jones
Author: Matthew Hooker
Author-email: mwhooker@gmail.com
License: Apache License 2.0
Platform: UNKNOWN
